{"nodes": [{"id": "d_kuliah_ta_new_folder_web_src_features_comparison_components_comparecharts_tsx", "label": "CompareCharts.tsx", "file_type": "code", "source_file": "D:\\Kuliah\\Ta\\New folder\\web\\src\\features\\comparison\\components\\CompareCharts.tsx", "source_location": "L1"}, {"id": "components_comparecharts_chart_colors", "label": "CHART_COLORS", "file_type": "code", "source_file": "D:\\Kuliah\\Ta\\New folder\\web\\src\\features\\comparison\\components\\CompareCharts.tsx", "source_location": "L22"}, {"id": "components_comparecharts_tooltippayload", "label": "TooltipPayload", "file_type": "code", "source_file": "D:\\Kuliah\\Ta\\New folder\\web\\src\\features\\comparison\\components\\CompareCharts.tsx", "source_location": "L30"}, {"id": "components_comparecharts_compareradarrow", "label": "CompareRadarRow", "file_type": "code", "source_file": "D:\\Kuliah\\Ta\\New folder\\web\\src\\features\\comparison\\components\\CompareCharts.tsx", "source_location": "L36"}, {"id": "components_comparecharts_comparesentimentrow", "label": "CompareSentimentRow", "file_type": "code", "source_file": "D:\\Kuliah\\Ta\\New folder\\web\\src\\features\\comparison\\components\\CompareCharts.tsx", "source_location": "L43"}, {"id": "components_comparecharts_comparechartsprops", "label": "CompareChartsProps", "file_type": "code", "source_file": "D:\\Kuliah\\Ta\\New folder\\web\\src\\features\\comparison\\components\\CompareCharts.tsx", "source_location": "L50"}, {"id": "components_comparecharts_customtooltip", "label": "CustomTooltip()", "file_type": "code", "source_file": "D:\\Kuliah\\Ta\\New folder\\web\\src\\features\\comparison\\components\\CompareCharts.tsx", "source_location": "L57"}, {"id": "components_comparecharts_comparecharts", "label": "CompareCharts()", "file_type": "code", "source_file": "D:\\Kuliah\\Ta\\New folder\\web\\src\\features\\comparison\\components\\CompareCharts.tsx", "source_location": "L76"}], "edges": [{"source": "d_kuliah_ta_new_folder_web_src_features_comparison_components_comparecharts_tsx", "target": "recharts", "relation": "imports_from", "context": "import", "confidence": "EXTRACTED", "source_file": "D:\\Kuliah\\Ta\\New folder\\web\\src\\features\\comparison\\components\\CompareCharts.tsx", "source_location": "L3", "weight": 1.0}, {"source": "d_kuliah_ta_new_folder_web_src_features_comparison_components_comparecharts_tsx", "target": "lucide_react", "relation": "imports_from", "context": "import", "confidence": "EXTRACTED", "source_file": "D:\\Kuliah\\Ta\\New folder\\web\\src\\features\\comparison\\components\\CompareCharts.tsx", "source_location": "L18", "weight": 1.0}, {"source": "d_kuliah_ta_new_folder_web_src_features_comparison_components_comparecharts_tsx", "target": "d_kuliah_ta_new_folder_web_src_components_charts_chartpanel_tsx", "relation": "imports_from", "context": "import", "confidence": "EXTRACTED", "source_file": "D:\\Kuliah\\Ta\\New folder\\web\\src\\features\\comparison\\components\\CompareCharts.tsx", "source_location": "L20", "weight": 1.0}, {"source": "d_kuliah_ta_new_folder_web_src_features_comparison_components_comparecharts_tsx", "target": "charts_chartpanel_chartpanel", "relation": "imports", "context": "import", "confidence": "EXTRACTED", "source_file": "D:\\Kuliah\\Ta\\New folder\\web\\src\\features\\comparison\\components\\CompareCharts.tsx", "source_location": "L20", "weight": 1.0}, {"source": "d_kuliah_ta_new_folder_web_src_features_comparison_components_comparecharts_tsx", "target": "components_comparecharts_chart_colors", "relation": "contains", "confidence": "EXTRACTED", "source_file": "D:\\Kuliah\\Ta\\New folder\\web\\src\\features\\comparison\\components\\CompareCharts.tsx", "source_location": "L22", "weight": 1.0}, {"source": "d_kuliah_ta_new_folder_web_src_features_comparison_components_comparecharts_tsx", "target": "components_comparecharts_tooltippayload", "relation": "contains", "confidence": "EXTRACTED", "source_file": "D:\\Kuliah\\Ta\\New folder\\web\\src\\features\\comparison\\components\\CompareCharts.tsx", "source_location": "L30", "weight": 1.0}, {"source": "d_kuliah_ta_new_folder_web_src_features_comparison_components_comparecharts_tsx", "target": "components_comparecharts_compareradarrow", "relation": "contains", "confidence": "EXTRACTED", "source_file": "D:\\Kuliah\\Ta\\New folder\\web\\src\\features\\comparison\\components\\CompareCharts.tsx", "source_location": "L36", "weight": 1.0}, {"source": "d_kuliah_ta_new_folder_web_src_features_comparison_components_comparecharts_tsx", "target": "components_comparecharts_comparesentimentrow", "relation": "contains", "confidence": "EXTRACTED", "source_file": "D:\\Kuliah\\Ta\\New folder\\web\\src\\features\\comparison\\components\\CompareCharts.tsx", "source_location": "L43", "weight": 1.0}, {"source": "d_kuliah_ta_new_folder_web_src_features_comparison_components_comparecharts_tsx", "target": "components_comparecharts_comparechartsprops", "relation": "contains", "confidence": "EXTRACTED", "source_file": "D:\\Kuliah\\Ta\\New folder\\web\\src\\features\\comparison\\components\\CompareCharts.tsx", "source_location": "L50", "weight": 1.0}, {"source": "d_kuliah_ta_new_folder_web_src_features_comparison_components_comparecharts_tsx", "target": "components_comparecharts_customtooltip", "relation": "contains", "confidence": "EXTRACTED", "source_file": "D:\\Kuliah\\Ta\\New folder\\web\\src\\features\\comparison\\components\\CompareCharts.tsx", "source_location": "L57", "weight": 1.0}, {"source": "d_kuliah_ta_new_folder_web_src_features_comparison_components_comparecharts_tsx", "target": "components_comparecharts_comparecharts", "relation": "contains", "confidence": "EXTRACTED", "source_file": "D:\\Kuliah\\Ta\\New folder\\web\\src\\features\\comparison\\components\\CompareCharts.tsx", "source_location": "L76", "weight": 1.0}], "raw_calls": [{"caller_nid": "components_comparecharts_customtooltip", "callee": "map", "is_member_call": true, "source_file": "D:\\Kuliah\\Ta\\New folder\\web\\src\\features\\comparison\\components\\CompareCharts.tsx", "source_location": "L64"}]}