{"nodes": [{"id": "d_kuliah_ta_new_folder_web_src_features_analytics_components_compare_compareclient_tsx", "label": "CompareClient.tsx", "file_type": "code", "source_file": "D:\\Kuliah\\Ta\\New folder\\web\\src\\features\\analytics\\components\\compare\\CompareClient.tsx", "source_location": "L1"}, {"id": "compare_compareclient_mode", "label": "Mode", "file_type": "code", "source_file": "D:\\Kuliah\\Ta\\New folder\\web\\src\\features\\analytics\\components\\compare\\CompareClient.tsx", "source_location": "L27"}, {"id": "compare_compareclient_destinationoption", "label": "DestinationOption", "file_type": "code", "source_file": "D:\\Kuliah\\Ta\\New folder\\web\\src\\features\\analytics\\components\\compare\\CompareClient.tsx", "source_location": "L29"}, {"id": "compare_compareclient_tone", "label": "Tone", "file_type": "code", "source_file": "D:\\Kuliah\\Ta\\New folder\\web\\src\\features\\analytics\\components\\compare\\CompareClient.tsx", "source_location": "L34"}, {"id": "compare_compareclient_tooltippayload", "label": "TooltipPayload", "file_type": "code", "source_file": "D:\\Kuliah\\Ta\\New folder\\web\\src\\features\\analytics\\components\\compare\\CompareClient.tsx", "source_location": "L36"}, {"id": "compare_compareclient_metricrow", "label": "MetricRow", "file_type": "code", "source_file": "D:\\Kuliah\\Ta\\New folder\\web\\src\\features\\analytics\\components\\compare\\CompareClient.tsx", "source_location": "L42"}, {"id": "compare_compareclient_sentiment_colors", "label": "SENTIMENT_COLORS", "file_type": "code", "source_file": "D:\\Kuliah\\Ta\\New folder\\web\\src\\features\\analytics\\components\\compare\\CompareClient.tsx", "source_location": "L52"}, {"id": "compare_compareclient_percent", "label": "percent()", "file_type": "code", "source_file": "D:\\Kuliah\\Ta\\New folder\\web\\src\\features\\analytics\\components\\compare\\CompareClient.tsx", "source_location": "L54"}, {"id": "compare_compareclient_sentimenttotal", "label": "sentimentTotal()", "file_type": "code", "source_file": "D:\\Kuliah\\Ta\\New folder\\web\\src\\features\\analytics\\components\\compare\\CompareClient.tsx", "source_location": "L58"}, {"id": "compare_compareclient_sentimentrate", "label": "sentimentRate()", "file_type": "code", "source_file": "D:\\Kuliah\\Ta\\New folder\\web\\src\\features\\analytics\\components\\compare\\CompareClient.tsx", "source_location": "L63"}, {"id": "compare_compareclient_formatmonth", "label": "formatMonth()", "file_type": "code", "source_file": "D:\\Kuliah\\Ta\\New folder\\web\\src\\features\\analytics\\components\\compare\\CompareClient.tsx", "source_location": "L68"}, {"id": "compare_compareclient_cleantopicname", "label": "cleanTopicName()", "file_type": "code", "source_file": "D:\\Kuliah\\Ta\\New folder\\web\\src\\features\\analytics\\components\\compare\\CompareClient.tsx", "source_location": "L72"}, {"id": "compare_compareclient_formatmetric", "label": "formatMetric()", "file_type": "code", "source_file": "D:\\Kuliah\\Ta\\New folder\\web\\src\\features\\analytics\\components\\compare\\CompareClient.tsx", "source_location": "L76"}, {"id": "compare_compareclient_formatsigned", "label": "formatSigned()", "file_type": "code", "source_file": "D:\\Kuliah\\Ta\\New folder\\web\\src\\features\\analytics\\components\\compare\\CompareClient.tsx", "source_location": "L82"}, {"id": "compare_compareclient_geterrormessage", "label": "getErrorMessage()", "file_type": "code", "source_file": "D:\\Kuliah\\Ta\\New folder\\web\\src\\features\\analytics\\components\\compare\\CompareClient.tsx", "source_location": "L87"}, {"id": "compare_compareclient_customtooltip", "label": "CustomTooltip()", "file_type": "code", "source_file": "D:\\Kuliah\\Ta\\New folder\\web\\src\\features\\analytics\\components\\compare\\CompareClient.tsx", "source_location": "L93"}, {"id": "compare_compareclient_compareclient", "label": "CompareClient()", "file_type": "code", "source_file": "D:\\Kuliah\\Ta\\New folder\\web\\src\\features\\analytics\\components\\compare\\CompareClient.tsx", "source_location": "L112"}], "edges": [{"source": "d_kuliah_ta_new_folder_web_src_features_analytics_components_compare_compareclient_tsx", "target": "react", "relation": "imports_from", "context": "import", "confidence": "EXTRACTED", "source_file": "D:\\Kuliah\\Ta\\New folder\\web\\src\\features\\analytics\\components\\compare\\CompareClient.tsx", "source_location": "L3", "weight": 1.0}, {"source": "d_kuliah_ta_new_folder_web_src_features_analytics_components_compare_compareclient_tsx", "target": "react", "relation": "imports_from", "context": "import", "confidence": "EXTRACTED", "source_file": "D:\\Kuliah\\Ta\\New folder\\web\\src\\features\\analytics\\components\\compare\\CompareClient.tsx", "source_location": "L4", "weight": 1.0}, {"source": "d_kuliah_ta_new_folder_web_src_features_analytics_components_compare_compareclient_tsx", "target": "lucide_react", "relation": "imports_from", "context": "import", "confidence": "EXTRACTED", "source_file": "D:\\Kuliah\\Ta\\New folder\\web\\src\\features\\analytics\\components\\compare\\CompareClient.tsx", "source_location": "L5", "weight": 1.0}, {"source": "d_kuliah_ta_new_folder_web_src_features_analytics_components_compare_compareclient_tsx", "target": "d_kuliah_ta_new_folder_web_src_features_admin_index_ts", "relation": "imports_from", "context": "import", "confidence": "EXTRACTED", "source_file": "D:\\Kuliah\\Ta\\New folder\\web\\src\\features\\analytics\\components\\compare\\CompareClient.tsx", "source_location": "L15", "weight": 1.0}, {"source": "d_kuliah_ta_new_folder_web_src_features_analytics_components_compare_compareclient_tsx", "target": "admin_index_admindestinationservice", "relation": "imports", "context": "import", "confidence": "EXTRACTED", "source_file": "D:\\Kuliah\\Ta\\New folder\\web\\src\\features\\analytics\\components\\compare\\CompareClient.tsx", "source_location": "L15", "weight": 1.0}, {"source": "d_kuliah_ta_new_folder_web_src_features_analytics_components_compare_compareclient_tsx", "target": "d_kuliah_ta_new_folder_web_src_features_analytics_services_analytics_service_ts", "relation": "imports_from", "context": "import", "confidence": "EXTRACTED", "source_file": "D:\\Kuliah\\Ta\\New folder\\web\\src\\features\\analytics\\components\\compare\\CompareClient.tsx", "source_location": "L16", "weight": 1.0}, {"source": "d_kuliah_ta_new_folder_web_src_features_analytics_components_compare_compareclient_tsx", "target": "services_analytics_service_adminanalyticsservice", "relation": "imports", "context": "import", "confidence": "EXTRACTED", "source_file": "D:\\Kuliah\\Ta\\New folder\\web\\src\\features\\analytics\\components\\compare\\CompareClient.tsx", "source_location": "L16", "weight": 1.0}, {"source": "d_kuliah_ta_new_folder_web_src_features_analytics_components_compare_compareclient_tsx", "target": "services_analytics_service_compareresult", "relation": "imports", "context": "import", "confidence": "EXTRACTED", "source_file": "D:\\Kuliah\\Ta\\New folder\\web\\src\\features\\analytics\\components\\compare\\CompareClient.tsx", "source_location": "L16", "weight": 1.0}, {"source": "d_kuliah_ta_new_folder_web_src_features_analytics_components_compare_compareclient_tsx", "target": "services_analytics_service_destinationanalytics", "relation": "imports", "context": "import", "confidence": "EXTRACTED", "source_file": "D:\\Kuliah\\Ta\\New folder\\web\\src\\features\\analytics\\components\\compare\\CompareClient.tsx", "source_location": "L16", "weight": 1.0}, {"source": "d_kuliah_ta_new_folder_web_src_features_analytics_components_compare_compareclient_tsx", "target": "services_analytics_service_topicdata", "relation": "imports", "context": "import", "confidence": "EXTRACTED", "source_file": "D:\\Kuliah\\Ta\\New folder\\web\\src\\features\\analytics\\components\\compare\\CompareClient.tsx", "source_location": "L16", "weight": 1.0}, {"source": "d_kuliah_ta_new_folder_web_src_features_analytics_components_compare_compareclient_tsx", "target": "services_analytics_service_trenddata", "relation": "imports", "context": "import", "confidence": "EXTRACTED", "source_file": "D:\\Kuliah\\Ta\\New folder\\web\\src\\features\\analytics\\components\\compare\\CompareClient.tsx", "source_location": "L16", "weight": 1.0}, {"source": "d_kuliah_ta_new_folder_web_src_features_analytics_components_compare_compareclient_tsx", "target": "d_kuliah_ta_new_folder_web_src_features_analytics_components_compare_admin_compare_result_tsx", "relation": "imports_from", "context": "import", "confidence": "EXTRACTED", "source_file": "D:\\Kuliah\\Ta\\New folder\\web\\src\\features\\analytics\\components\\compare\\CompareClient.tsx", "source_location": "L23", "weight": 1.0}, {"source": "d_kuliah_ta_new_folder_web_src_features_analytics_components_compare_compareclient_tsx", "target": "compare_admin_compare_result_compareanalysisview", "relation": "imports", "context": "import", "confidence": "EXTRACTED", "source_file": "D:\\Kuliah\\Ta\\New folder\\web\\src\\features\\analytics\\components\\compare\\CompareClient.tsx", "source_location": "L23", "weight": 1.0}, {"source": "d_kuliah_ta_new_folder_web_src_features_analytics_components_compare_compareclient_tsx", "target": "d_kuliah_ta_new_folder_web_src_features_analytics_components_compare_admin_compare_skeleton_tsx", "relation": "imports_from", "context": "import", "confidence": "EXTRACTED", "source_file": "D:\\Kuliah\\Ta\\New folder\\web\\src\\features\\analytics\\components\\compare\\CompareClient.tsx", "source_location": "L24", "weight": 1.0}, {"source": "d_kuliah_ta_new_folder_web_src_features_analytics_components_compare_compareclient_tsx", "target": "compare_admin_compare_skeleton_analyticsskeleton", "relation": "imports", "context": "import", "confidence": "EXTRACTED", "source_file": "D:\\Kuliah\\Ta\\New folder\\web\\src\\features\\analytics\\components\\compare\\CompareClient.tsx", "source_location": "L24", "weight": 1.0}, {"source": "d_kuliah_ta_new_folder_web_src_features_analytics_components_compare_compareclient_tsx", "target": "d_kuliah_ta_new_folder_web_src_features_analytics_components_compare_admin_compare_panels_tsx", "relation": "imports_from", "context": "import", "confidence": "EXTRACTED", "source_file": "D:\\Kuliah\\Ta\\New folder\\web\\src\\features\\analytics\\components\\compare\\CompareClient.tsx", "source_location": "L25", "weight": 1.0}, {"source": "d_kuliah_ta_new_folder_web_src_features_analytics_components_compare_compareclient_tsx", "target": "compare_admin_compare_panels_comparisonheropanel", "relation": "imports", "context": "import", "confidence": "EXTRACTED", "source_file": "D:\\Kuliah\\Ta\\New folder\\web\\src\\features\\analytics\\components\\compare\\CompareClient.tsx", "source_location": "L25", "weight": 1.0}, {"source": "d_kuliah_ta_new_folder_web_src_features_analytics_components_compare_compareclient_tsx", "target": "compare_admin_compare_panels_destinationselect", "relation": "imports", "context": "import", "confidence": "EXTRACTED", "source_file": "D:\\Kuliah\\Ta\\New folder\\web\\src\\features\\analytics\\components\\compare\\CompareClient.tsx", "source_location": "L25", "weight": 1.0}, {"source": "d_kuliah_ta_new_folder_web_src_features_analytics_components_compare_compareclient_tsx", "target": "compare_compareclient_mode", "relation": "contains", "confidence": "EXTRACTED", "source_file": "D:\\Kuliah\\Ta\\New folder\\web\\src\\features\\analytics\\components\\compare\\CompareClient.tsx", "source_location": "L27", "weight": 1.0}, {"source": "d_kuliah_ta_new_folder_web_src_features_analytics_components_compare_compareclient_tsx", "target": "compare_compareclient_destinationoption", "relation": "contains", "confidence": "EXTRACTED", "source_file": "D:\\Kuliah\\Ta\\New folder\\web\\src\\features\\analytics\\components\\compare\\CompareClient.tsx", "source_location": "L29", "weight": 1.0}, {"source": "d_kuliah_ta_new_folder_web_src_features_analytics_components_compare_compareclient_tsx", "target": "compare_compareclient_tone", "relation": "contains", "confidence": "EXTRACTED", "source_file": "D:\\Kuliah\\Ta\\New folder\\web\\src\\features\\analytics\\components\\compare\\CompareClient.tsx", "source_location": "L34", "weight": 1.0}, {"source": "d_kuliah_ta_new_folder_web_src_features_analytics_components_compare_compareclient_tsx", "target": "compare_compareclient_tooltippayload", "relation": "contains", "confidence": "EXTRACTED", "source_file": "D:\\Kuliah\\Ta\\New folder\\web\\src\\features\\analytics\\components\\compare\\CompareClient.tsx", "source_location": "L36", "weight": 1.0}, {"source": "d_kuliah_ta_new_folder_web_src_features_analytics_components_compare_compareclient_tsx", "target": "compare_compareclient_metricrow", "relation": "contains", "confidence": "EXTRACTED", "source_file": "D:\\Kuliah\\Ta\\New folder\\web\\src\\features\\analytics\\components\\compare\\CompareClient.tsx", "source_location": "L42", "weight": 1.0}, {"source": "d_kuliah_ta_new_folder_web_src_features_analytics_components_compare_compareclient_tsx", "target": "compare_compareclient_sentiment_colors", "relation": "contains", "confidence": "EXTRACTED", "source_file": "D:\\Kuliah\\Ta\\New folder\\web\\src\\features\\analytics\\components\\compare\\CompareClient.tsx", "source_location": "L52", "weight": 1.0}, {"source": "d_kuliah_ta_new_folder_web_src_features_analytics_components_compare_compareclient_tsx", "target": "compare_compareclient_percent", "relation": "contains", "confidence": "EXTRACTED", "source_file": "D:\\Kuliah\\Ta\\New folder\\web\\src\\features\\analytics\\components\\compare\\CompareClient.tsx", "source_location": "L54", "weight": 1.0}, {"source": "d_kuliah_ta_new_folder_web_src_features_analytics_components_compare_compareclient_tsx", "target": "compare_compareclient_sentimenttotal", "relation": "contains", "confidence": "EXTRACTED", "source_file": "D:\\Kuliah\\Ta\\New folder\\web\\src\\features\\analytics\\components\\compare\\CompareClient.tsx", "source_location": "L58", "weight": 1.0}, {"source": "d_kuliah_ta_new_folder_web_src_features_analytics_components_compare_compareclient_tsx", "target": "compare_compareclient_sentimentrate", "relation": "contains", "confidence": "EXTRACTED", "source_file": "D:\\Kuliah\\Ta\\New folder\\web\\src\\features\\analytics\\components\\compare\\CompareClient.tsx", "source_location": "L63", "weight": 1.0}, {"source": "d_kuliah_ta_new_folder_web_src_features_analytics_components_compare_compareclient_tsx", "target": "compare_compareclient_formatmonth", "relation": "contains", "confidence": "EXTRACTED", "source_file": "D:\\Kuliah\\Ta\\New folder\\web\\src\\features\\analytics\\components\\compare\\CompareClient.tsx", "source_location": "L68", "weight": 1.0}, {"source": "d_kuliah_ta_new_folder_web_src_features_analytics_components_compare_compareclient_tsx", "target": "compare_compareclient_cleantopicname", "relation": "contains", "confidence": "EXTRACTED", "source_file": "D:\\Kuliah\\Ta\\New folder\\web\\src\\features\\analytics\\components\\compare\\CompareClient.tsx", "source_location": "L72", "weight": 1.0}, {"source": "d_kuliah_ta_new_folder_web_src_features_analytics_components_compare_compareclient_tsx", "target": "compare_compareclient_formatmetric", "relation": "contains", "confidence": "EXTRACTED", "source_file": "D:\\Kuliah\\Ta\\New folder\\web\\src\\features\\analytics\\components\\compare\\CompareClient.tsx", "source_location": "L76", "weight": 1.0}, {"source": "d_kuliah_ta_new_folder_web_src_features_analytics_components_compare_compareclient_tsx", "target": "compare_compareclient_formatsigned", "relation": "contains", "confidence": "EXTRACTED", "source_file": "D:\\Kuliah\\Ta\\New folder\\web\\src\\features\\analytics\\components\\compare\\CompareClient.tsx", "source_location": "L82", "weight": 1.0}, {"source": "d_kuliah_ta_new_folder_web_src_features_analytics_components_compare_compareclient_tsx", "target": "compare_compareclient_geterrormessage", "relation": "contains", "confidence": "EXTRACTED", "source_file": "D:\\Kuliah\\Ta\\New folder\\web\\src\\features\\analytics\\components\\compare\\CompareClient.tsx", "source_location": "L87", "weight": 1.0}, {"source": "d_kuliah_ta_new_folder_web_src_features_analytics_components_compare_compareclient_tsx", "target": "compare_compareclient_customtooltip", "relation": "contains", "confidence": "EXTRACTED", "source_file": "D:\\Kuliah\\Ta\\New folder\\web\\src\\features\\analytics\\components\\compare\\CompareClient.tsx", "source_location": "L93", "weight": 1.0}, {"source": "d_kuliah_ta_new_folder_web_src_features_analytics_components_compare_compareclient_tsx", "target": "compare_compareclient_compareclient", "relation": "contains", "confidence": "EXTRACTED", "source_file": "D:\\Kuliah\\Ta\\New folder\\web\\src\\features\\analytics\\components\\compare\\CompareClient.tsx", "source_location": "L112", "weight": 1.0}, {"source": "compare_compareclient_sentimentrate", "target": "compare_compareclient_sentimenttotal", "relation": "calls", "context": "call", "confidence": "EXTRACTED", "source_file": "D:\\Kuliah\\Ta\\New folder\\web\\src\\features\\analytics\\components\\compare\\CompareClient.tsx", "source_location": "L64", "weight": 1.0}], "raw_calls": [{"caller_nid": "compare_compareclient_percent", "callee": "round", "is_member_call": true, "source_file": "D:\\Kuliah\\Ta\\New folder\\web\\src\\features\\analytics\\components\\compare\\CompareClient.tsx", "source_location": "L55"}, {"caller_nid": "compare_compareclient_sentimentrate", "callee": "round", "is_member_call": true, "source_file": "D:\\Kuliah\\Ta\\New folder\\web\\src\\features\\analytics\\components\\compare\\CompareClient.tsx", "source_location": "L65"}, {"caller_nid": "compare_compareclient_formatmonth", "callee": "toLocaleDateString", "is_member_call": true, "source_file": "D:\\Kuliah\\Ta\\New folder\\web\\src\\features\\analytics\\components\\compare\\CompareClient.tsx", "source_location": "L69"}, {"caller_nid": "compare_compareclient_cleantopicname", "callee": "trim", "is_member_call": true, "source_file": "D:\\Kuliah\\Ta\\New folder\\web\\src\\features\\analytics\\components\\compare\\CompareClient.tsx", "source_location": "L73"}, {"caller_nid": "compare_compareclient_cleantopicname", "callee": "replace", "is_member_call": true, "source_file": "D:\\Kuliah\\Ta\\New folder\\web\\src\\features\\analytics\\components\\compare\\CompareClient.tsx", "source_location": "L73"}, {"caller_nid": "compare_compareclient_formatmetric", "callee": "round", "is_member_call": true, "source_file": "D:\\Kuliah\\Ta\\New folder\\web\\src\\features\\analytics\\components\\compare\\CompareClient.tsx", "source_location": "L77"}, {"caller_nid": "compare_compareclient_formatmetric", "callee": "toFixed", "is_member_call": true, "source_file": "D:\\Kuliah\\Ta\\New folder\\web\\src\\features\\analytics\\components\\compare\\CompareClient.tsx", "source_location": "L78"}, {"caller_nid": "compare_compareclient_formatmetric", "callee": "toFixed", "is_member_call": true, "source_file": "D:\\Kuliah\\Ta\\New folder\\web\\src\\features\\analytics\\components\\compare\\CompareClient.tsx", "source_location": "L79"}, {"caller_nid": "compare_compareclient_customtooltip", "callee": "map", "is_member_call": true, "source_file": "D:\\Kuliah\\Ta\\New folder\\web\\src\\features\\analytics\\components\\compare\\CompareClient.tsx", "source_location": "L100"}, {"caller_nid": "compare_compareclient_compareclient", "callee": "useState", "is_member_call": false, "source_file": "D:\\Kuliah\\Ta\\New folder\\web\\src\\features\\analytics\\components\\compare\\CompareClient.tsx", "source_location": "L114"}, {"caller_nid": "compare_compareclient_compareclient", "callee": "useState", "is_member_call": false, "source_file": "D:\\Kuliah\\Ta\\New folder\\web\\src\\features\\analytics\\components\\compare\\CompareClient.tsx", "source_location": "L115"}, {"caller_nid": "compare_compareclient_compareclient", "callee": "useState", "is_member_call": false, "source_file": "D:\\Kuliah\\Ta\\New folder\\web\\src\\features\\analytics\\components\\compare\\CompareClient.tsx", "source_location": "L116"}, {"caller_nid": "compare_compareclient_compareclient", "callee": "useState", "is_member_call": false, "source_file": "D:\\Kuliah\\Ta\\New folder\\web\\src\\features\\analytics\\components\\compare\\CompareClient.tsx", "source_location": "L117"}, {"caller_nid": "compare_compareclient_compareclient", "callee": "useState", "is_member_call": false, "source_file": "D:\\Kuliah\\Ta\\New folder\\web\\src\\features\\analytics\\components\\compare\\CompareClient.tsx", "source_location": "L118"}, {"caller_nid": "compare_compareclient_compareclient", "callee": "useState", "is_member_call": false, "source_file": "D:\\Kuliah\\Ta\\New folder\\web\\src\\features\\analytics\\components\\compare\\CompareClient.tsx", "source_location": "L119"}, {"caller_nid": "compare_compareclient_compareclient", "callee": "useState", "is_member_call": false, "source_file": "D:\\Kuliah\\Ta\\New folder\\web\\src\\features\\analytics\\components\\compare\\CompareClient.tsx", "source_location": "L120"}, {"caller_nid": "compare_compareclient_compareclient", "callee": "useState", "is_member_call": false, "source_file": "D:\\Kuliah\\Ta\\New folder\\web\\src\\features\\analytics\\components\\compare\\CompareClient.tsx", "source_location": "L121"}, {"caller_nid": "compare_compareclient_compareclient", "callee": "useState", "is_member_call": false, "source_file": "D:\\Kuliah\\Ta\\New folder\\web\\src\\features\\analytics\\components\\compare\\CompareClient.tsx", "source_location": "L122"}, {"caller_nid": "compare_compareclient_compareclient", "callee": "useState", "is_member_call": false, "source_file": "D:\\Kuliah\\Ta\\New folder\\web\\src\\features\\analytics\\components\\compare\\CompareClient.tsx", "source_location": "L123"}, {"caller_nid": "compare_compareclient_compareclient", "callee": "useEffect", "is_member_call": false, "source_file": "D:\\Kuliah\\Ta\\New folder\\web\\src\\features\\analytics\\components\\compare\\CompareClient.tsx", "source_location": "L125"}, {"caller_nid": "compare_compareclient_compareclient", "callee": "useEffect", "is_member_call": false, "source_file": "D:\\Kuliah\\Ta\\New folder\\web\\src\\features\\analytics\\components\\compare\\CompareClient.tsx", "source_location": "L148"}, {"caller_nid": "compare_compareclient_compareclient", "callee": "find", "is_member_call": true, "source_file": "D:\\Kuliah\\Ta\\New folder\\web\\src\\features\\analytics\\components\\compare\\CompareClient.tsx", "source_location": "L195"}, {"caller_nid": "compare_compareclient_compareclient", "callee": "find", "is_member_call": true, "source_file": "D:\\Kuliah\\Ta\\New folder\\web\\src\\features\\analytics\\components\\compare\\CompareClient.tsx", "source_location": "L196"}, {"caller_nid": "compare_compareclient_compareclient", "callee": "useMemo", "is_member_call": false, "source_file": "D:\\Kuliah\\Ta\\New folder\\web\\src\\features\\analytics\\components\\compare\\CompareClient.tsx", "source_location": "L198"}, {"caller_nid": "compare_compareclient_compareclient", "callee": "useMemo", "is_member_call": false, "source_file": "D:\\Kuliah\\Ta\\New folder\\web\\src\\features\\analytics\\components\\compare\\CompareClient.tsx", "source_location": "L210"}, {"caller_nid": "compare_compareclient_compareclient", "callee": "useMemo", "is_member_call": false, "source_file": "D:\\Kuliah\\Ta\\New folder\\web\\src\\features\\analytics\\components\\compare\\CompareClient.tsx", "source_location": "L222"}, {"caller_nid": "compare_compareclient_compareclient", "callee": "useMemo", "is_member_call": false, "source_file": "D:\\Kuliah\\Ta\\New folder\\web\\src\\features\\analytics\\components\\compare\\CompareClient.tsx", "source_location": "L240"}, {"caller_nid": "compare_compareclient_compareclient", "callee": "useMemo", "is_member_call": false, "source_file": "D:\\Kuliah\\Ta\\New folder\\web\\src\\features\\analytics\\components\\compare\\CompareClient.tsx", "source_location": "L251"}, {"caller_nid": "compare_compareclient_compareclient", "callee": "useMemo", "is_member_call": false, "source_file": "D:\\Kuliah\\Ta\\New folder\\web\\src\\features\\analytics\\components\\compare\\CompareClient.tsx", "source_location": "L264"}]}